ddfirmware/__init__.py
ddfirmware/cli.py
ddfirmware-1.0.1.dist-info/LICENSE
ddfirmware-1.0.1.dist-info/METADATA
ddfirmware-1.0.1.dist-info/WHEEL
ddfirmware-1.0.1.dist-info/entry_points.txt
ddfirmware-1.0.1.dist-info/top_level.txt
ddfirmware-1.0.1.dist-info/RECORD
