Metadata-Version: 2.1
Name: ddfirmware
Version: 1.0.1
Summary: DD-WRT firmware download tool
Home-page: https://github.com/fleetyeets/dd-firmware
Author: Travis Pawlikowski
Author-email: tnp123@protonmail.com
License: UNKNOWN
Project-URL: Bug Reports, https://github.com/fleetyeets/dd-firmware/issues
Project-URL: Source, https://github.com/fleetyeets/dd-firmware
Platform: UNKNOWN
Classifier: Programming Language :: Python :: 3
Classifier: Development Status :: 5 - Production/Stable
Classifier: License :: OSI Approved :: GNU General Public License v3 (GPLv3)
Classifier: Operating System :: OS Independent
Requires-Python: >=3.0
License-File: LICENSE
